py_model_versioning/__init__.py
py_model_versioning/main.py
py_model_versioning/classes/__init__.py
py_model_versioning/classes/func.py
py_model_versioning/classes/google_storage.py
py_model_versioning-0.5.dist-info/METADATA
py_model_versioning-0.5.dist-info/WHEEL
py_model_versioning-0.5.dist-info/entry_points.txt
py_model_versioning-0.5.dist-info/top_level.txt
py_model_versioning-0.5.dist-info/RECORD
