Metadata-Version: 2.1
Name: py-model-versioning
Version: 0.5
Requires-Python: >=3.7
Requires-Dist: requests
Requires-Dist: click (==8.1.3)
Requires-Dist: locust (==1.0)
Requires-Dist: numpy (==1.23.2)
Requires-Dist: pandas (==1.4.4)
Requires-Dist: protobuf (==4.21.5)
Requires-Dist: tqdm (==4.64.1)
Requires-Dist: google-cloud-storage (==2.5.0)
Requires-Dist: importlib ; python_version > "3.7"
